[
  {
    "designation_id": "18",
    "designation_name": "PRINCIPAL",
    "entered_by": null,
    "entry_timestamp": null,
    "last_updated_by": null,
    "last_updated_timestamp": null,
    "profession_type": null,
    "desig_code": "18",
    "desig_id": "1",
    "subject_name": null,
    "designation_name_bn": "অধ্যাক্ষ"
  },
  {
    "designation_id": "19",
    "designation_name": "VICE PRINCIPAL",
    "entered_by": null,
    "entry_timestamp": null,
    "last_updated_by": null,
    "last_updated_timestamp": null,
    "profession_type": null,
    "desig_code": "19",
    "desig_id": "2",
    "subject_name": null,
    "designation_name_bn": "উপাধ্যাক্ষ"
  },
  {
    "designation_id": "20",
    "designation_name": "PROFESSOR ",
    "entered_by": null,
    "entry_timestamp": null,
    "last_updated_by": null,
    "last_updated_timestamp": null,
    "profession_type": null,
    "desig_code": "20",
    "desig_id": "3",
    "subject_name": null,
    "designation_name_bn": "অধ্যাপক"
  },
  {
    "designation_id": "21",
    "designation_name": "ASSOCIATE PROFESSOR",
    "entered_by": null,
    "entry_timestamp": null,
    "last_updated_by": null,
    "last_updated_timestamp": null,
    "profession_type": null,
    "desig_code": "21",
    "desig_id": "4",
    "subject_name": null,
    "designation_name_bn": "সহযোগী অধ্যাপক"
  },
  {
    "designation_id": "22",
    "designation_name": "ASSISTANT PROFESSOR ",
    "entered_by": null,
    "entry_timestamp": null,
    "last_updated_by": null,
    "last_updated_timestamp": null,
    "profession_type": null,
    "desig_code": "22",
    "desig_id": "5",
    "subject_name": null,
    "designation_name_bn": "সহকারি অধ্যাপক"
  },
  {
    "designation_id": "152",
    "designation_name": "SENIOR LECTURER",
    "entered_by": null,
    "entry_timestamp": null,
    "last_updated_by": null,
    "last_updated_timestamp": null,
    "profession_type": null,
    "desig_code": "152",
    "desig_id": "6",
    "subject_name": null,
    "designation_name_bn": "জ্যোষ্ঠ প্রভাষক"
  },
  {
    "designation_id": "23",
    "designation_name": "LECTURER ",
    "entered_by": null,
    "entry_timestamp": null,
    "last_updated_by": null,
    "last_updated_timestamp": null,
    "profession_type": null,
    "desig_code": "23",
    "desig_id": "7",
    "subject_name": null,
    "designation_name_bn": "প্রভাষক"
  },
  {
    "designation_id": "24",
    "designation_name": "DEMONSTRATOR ",
    "entered_by": null,
    "entry_timestamp": null,
    "last_updated_by": null,
    "last_updated_timestamp": null,
    "profession_type": null,
    "desig_code": "24",
    "desig_id": "8",
    "subject_name": null,
    "designation_name_bn": "প্রদর্শক"
  },
  {
    "designation_id": "06",
    "designation_name": "PHYSICAL TEACHER  ",
    "entered_by": null,
    "entry_timestamp": null,
    "last_updated_by": null,
    "last_updated_timestamp": null,
    "profession_type": null,
    "desig_code": "06",
    "desig_id": "9",
    "subject_name": null,
    "designation_name_bn": "শরীর চর্চা শিক্ষক"
  },
  {
    "designation_id": "40",
    "designation_name": "ASSISTANT TEACHER(LIBRARY SCIENCE)",
    "entered_by": null,
    "entry_timestamp": null,
    "last_updated_by": null,
    "last_updated_timestamp": null,
    "profession_type": null,
    "desig_code": "40",
    "desig_id": "10",
    "subject_name": null,
    "designation_name_bn": "সহকারী শিক্ষক (গ্রন্থাগার ও তথ্যবিজ্ঞান)"
  },
  {
    "designation_id": "41",
    "designation_name": "ASSISTANT LIBRARIAN CUM CATALOGER ",
    "entered_by": null,
    "entry_timestamp": null,
    "last_updated_by": null,
    "last_updated_timestamp": null,
    "profession_type": null,
    "desig_code": "41",
    "desig_id": "11",
    "subject_name": null,
    "designation_name_bn": "সহকারি লাইব্রেরিয়ান কাম ক্যাটালগার"
  },
  {
    "designation_id": "153",
    "designation_name": "OFFICE ASSISTANT CUM ACCOUNTANT ASSISTANT",
    "entered_by": null,
    "entry_timestamp": null,
    "last_updated_by": null,
    "last_updated_timestamp": null,
    "profession_type": null,
    "desig_code": "153",
    "desig_id": "12",
    "subject_name": null,
    "designation_name_bn": "অফিস সহকারী কাম হিসাব সহকারী"
  },
  {
    "designation_id": "154",
    "designation_name": "OFFICE ASSISTANT CUM COM OPERATOR",
    "entered_by": null,
    "entry_timestamp": null,
    "last_updated_by": null,
    "last_updated_timestamp": null,
    "profession_type": null,
    "desig_code": "154",
    "desig_id": "13",
    "subject_name": null,
    "designation_name_bn": "অফিস সহকারী কাম কম্পিউটার অপারেটর"
  },
  {
    "designation_id": "62",
    "designation_name": "RESEARCH / LAB ASSISTANT ",
    "entered_by": null,
    "entry_timestamp": null,
    "last_updated_by": null,
    "last_updated_timestamp": null,
    "profession_type": null,
    "desig_code": "62",
    "desig_id": "14",
    "subject_name": null,
    "designation_name_bn": "ল্যাব সহকারী"
  },
  {
    "designation_id": "50",
    "designation_name": "OFFICE ASSISTANCE",
    "entered_by": null,
    "entry_timestamp": null,
    "last_updated_by": null,
    "last_updated_timestamp": null,
    "profession_type": null,
    "desig_code": "50",
    "desig_id": "15",
    "subject_name": null,
    "designation_name_bn": "অফিস সহায়ক"
  },
  {
    "designation_id": "161",
    "designation_name": "SECURITY GOURD ",
    "entered_by": null,
    "entry_timestamp": null,
    "last_updated_by": null,
    "last_updated_timestamp": null,
    "profession_type": null,
    "desig_code": "161",
    "desig_id": "16",
    "subject_name": null,
    "designation_name_bn": "নিরাপত্তা কর্মী "
  },
  {
    "designation_id": "155",
    "designation_name": "CLEANER",
    "entered_by": null,
    "entry_timestamp": null,
    "last_updated_by": null,
    "last_updated_timestamp": null,
    "profession_type": null,
    "desig_code": "155",
    "desig_id": "17",
    "subject_name": null,
    "designation_name_bn": "পরিচ্ছন্নতা কর্মী"
  },
  {
    "designation_id": "163",
    "designation_name": "NIGHT GOURD ",
    "entered_by": null,
    "entry_timestamp": null,
    "last_updated_by": null,
    "last_updated_timestamp": null,
    "profession_type": null,
    "desig_code": "163",
    "desig_id": "18",
    "subject_name": null,
    "designation_name_bn": "নৈশ প্রহরী"
  },
  {
    "designation_id": "164",
    "designation_name": "AYA ",
    "entered_by": null,
    "entry_timestamp": null,
    "last_updated_by": null,
    "last_updated_timestamp": null,
    "profession_type": null,
    "desig_code": "164",
    "desig_id": "19",
    "subject_name": null,
    "designation_name_bn": "আয়া"
  }
]